[
    {
        "tweetID": 1113009339743100928,
        "financeType": "doge",
        "date": "2019-04-02",
        "fullText": "Dogecoin might be my fav cryptocurrency. It’s pretty cool.",
        "replyCount": 558,
        "likesCount": 9063,
        "retweetCount": 2428,
        "sentimentScore": 8.176000000000000e-001,
        "id": 5723,
        "adjustedClose": 2.795000000000000e-003,
        "volume": 60298362
    },
    {
        "tweetID": 1113173498384441344,
        "financeType": "doge",
        "date": "2019-04-02",
        "fullText": "Dogecoin rulz",
        "replyCount": 1732,
        "likesCount": 138893,
        "retweetCount": 16539,
        "sentimentScore": 0.000000000000000e+000,
        "id": 5723,
        "adjustedClose": 2.795000000000000e-003,
        "volume": 60298362
    },
    {
        "tweetID": 1113178951403180032,
        "financeType": "doge",
        "date": "2019-04-02",
        "fullText": "Dogecoin value may vary",
        "replyCount": 1080,
        "likesCount": 20160,
        "retweetCount": 1959,
        "sentimentScore": 3.400000000000000e-001,
        "id": 5723,
        "adjustedClose": 2.795000000000000e-003,
        "volume": 60298362
    },
    {
        "tweetID": 1254039929333649408,
        "financeType": "doge",
        "date": "2020-04-25",
        "fullText": "Dogecoin Mode",
        "replyCount": 124,
        "likesCount": 2192,
        "retweetCount": 207,
        "sentimentScore": 0.000000000000000e+000,
        "id": 6112,
        "adjustedClose": 2.142000000000000e-003,
        "volume": 229810398
    },
    {
        "tweetID": 1284290215561986048,
        "financeType": "doge",
        "date": "2020-07-18",
        "fullText": "Excuse me, I only sell Doge!",
        "replyCount": 416,
        "likesCount": 15930,
        "retweetCount": 775,
        "sentimentScore": 1.511000000000000e-001,
        "id": 6196,
        "adjustedClose": 3.473000000000000e-003,
        "volume": 204080851
    },
    {
        "tweetID": 1328771222822400000,
        "financeType": "doge",
        "date": "2020-11-17",
        "fullText": "Dojo\/Doge",
        "replyCount": 81,
        "likesCount": 1002,
        "retweetCount": 62,
        "sentimentScore": 0.000000000000000e+000,
        "id": 6318,
        "adjustedClose": 2.936000000000000e-003,
        "volume": 46631464
    },
    {
        "tweetID": 1340590280848908288,
        "financeType": "doge",
        "date": "2020-12-20",
        "fullText": "One word: Doge",
        "replyCount": 11227,
        "likesCount": 224342,
        "retweetCount": 26570,
        "sentimentScore": 0.000000000000000e+000,
        "id": 6351,
        "adjustedClose": 4.625000000000000e-003,
        "volume": 508066004
    },
    {
        "tweetID": 1357231313376456704,
        "financeType": "doge",
        "date": "2021-02-04",
        "fullText": "Doge",
        "replyCount": 21,
        "likesCount": 536,
        "retweetCount": 25,
        "sentimentScore": 0.000000000000000e+000,
        "id": 6397,
        "adjustedClose": 5.328900000000000e-002,
        "volume": 13040837601
    },
    {
        "tweetID": 1357241340313141248,
        "financeType": "doge",
        "date": "2021-02-04",
        "fullText": "Dogecoin is the people’s crypto",
        "replyCount": 18465,
        "likesCount": 533684,
        "retweetCount": 97994,
        "sentimentScore": 0.000000000000000e+000,
        "id": 6397,
        "adjustedClose": 5.328900000000000e-002,
        "volume": 13040837601
    },
    {
        "tweetID": 1357244295091208192,
        "financeType": "doge",
        "date": "2021-02-04",
        "fullText": "No highs, no lows, only Doge",
        "replyCount": 21310,
        "likesCount": 744715,
        "retweetCount": 107141,
        "sentimentScore": -6.369000000000000e-001,
        "id": 6397,
        "adjustedClose": 5.328900000000000e-002,
        "volume": 13040837601
    },
    {
        "tweetID": 1357972904663687168,
        "financeType": "doge",
        "date": "2021-02-06",
        "fullText": "Dogecake",
        "replyCount": 21,
        "likesCount": 536,
        "retweetCount": 25,
        "sentimentScore": 0.000000000000000e+000,
        "id": 6399,
        "adjustedClose": 5.759500000000000e-002,
        "volume": 5946101275
    },
    {
        "tweetID": 1358542364948668416,
        "financeType": "doge",
        "date": "2021-02-08",
        "fullText": "?? Who let the Doge out ??",
        "replyCount": 87,
        "likesCount": 3783,
        "retweetCount": 114,
        "sentimentScore": 0.000000000000000e+000,
        "id": 6401,
        "adjustedClose": 7.882500000000001e-002,
        "volume": 12844375210
    },
    {
        "tweetID": 1358648653573992448,
        "financeType": "doge",
        "date": "2021-02-08",
        "fullText": "Doge appears to be inflationary, but is not meaningfully so (fixed # of coins per unit time), whereas BTC is arguably deflationary to a fault. Transaction speed of Doge should ideally be a few orders of magnitude faster.",
        "replyCount": 87,
        "likesCount": 3783,
        "retweetCount": 114,
        "sentimentScore": -3.291000000000000e-001,
        "id": 6401,
        "adjustedClose": 7.882500000000001e-002,
        "volume": 12844375210
    },
    {
        "tweetID": 1359519541219500032,
        "financeType": "doge",
        "date": "2021-02-10",
        "fullText": "Bought some Dogecoin for lil X, so he can be a toddler hodler",
        "replyCount": 129,
        "likesCount": 1446,
        "retweetCount": 106,
        "sentimentScore": 0.000000000000000e+000,
        "id": 6403,
        "adjustedClose": 7.289600000000000e-002,
        "volume": 6785088422
    },
    {
        "tweetID": 1359791422711492608,
        "financeType": "doge",
        "date": "2021-02-11",
        "fullText": "Frodo was the underdoge, All thought he would fail, Himself most of all.",
        "replyCount": 129,
        "likesCount": 1446,
        "retweetCount": 106,
        "sentimentScore": -5.423000000000000e-001,
        "id": 6404,
        "adjustedClose": 6.967600000000000e-002,
        "volume": 3818556739
    },
    {
        "tweetID": 1360007611781795840,
        "financeType": "doge",
        "date": "2021-02-12",
        "fullText": "Doge is underestimated",
        "replyCount": 238,
        "likesCount": 30121,
        "retweetCount": 2069,
        "sentimentScore": -2.732000000000000e-001,
        "id": 6405,
        "adjustedClose": 7.006900000000001e-002,
        "volume": 4190843784
    },
    {
        "tweetID": 1361094185412100096,
        "financeType": "doge",
        "date": "2021-02-15",
        "fullText": "If major Dogecoin holders sell most of their coins, it will get my full support. Too much concentration is the only real issue imo.",
        "replyCount": 238,
        "likesCount": 30121,
        "retweetCount": 2069,
        "sentimentScore": 4.019000000000000e-001,
        "id": 6408,
        "adjustedClose": 5.659100000000000e-002,
        "volume": 4944804938
    },
    {
        "tweetID": 1361096223428653056,
        "financeType": "doge",
        "date": "2021-02-15",
        "fullText": "An acceptable percentage. Doge is much more concentrated.",
        "replyCount": 68,
        "likesCount": 3609,
        "retweetCount": 200,
        "sentimentScore": 3.182000000000000e-001,
        "id": 6408,
        "adjustedClose": 5.659100000000000e-002,
        "volume": 4944804938
    },
    {
        "tweetID": 1363046350900785152,
        "financeType": "doge",
        "date": "2021-02-20",
        "fullText": "I just set up some little Doge mining rigs with my kids. It was fun.",
        "replyCount": 68,
        "likesCount": 3609,
        "retweetCount": 200,
        "sentimentScore": 5.106000000000001e-001,
        "id": 6413,
        "adjustedClose": 5.438400000000000e-002,
        "volume": 3175468554
    },
    {
        "tweetID": 1363601164344823808,
        "financeType": "doge",
        "date": "2021-02-22",
        "fullText": "Dojo 4 Doge",
        "replyCount": 26,
        "likesCount": 1685,
        "retweetCount": 53,
        "sentimentScore": 0.000000000000000e+000,
        "id": 6415,
        "adjustedClose": 5.372500000000000e-002,
        "volume": 3366757324
    },
    {
        "tweetID": 1366477626429169664,
        "financeType": "doge",
        "date": "2021-03-01",
        "fullText": "Doge meme shield (legendary item)",
        "replyCount": 26,
        "likesCount": 1685,
        "retweetCount": 53,
        "sentimentScore": 0.000000000000000e+000,
        "id": 6422,
        "adjustedClose": 5.059900000000000e-002,
        "volume": 1494427207
    },
    {
        "tweetID": 1366668744748007424,
        "financeType": "doge",
        "date": "2021-03-02",
        "fullText": "2022: Dogecoin is dumb",
        "replyCount": 62,
        "likesCount": 1347,
        "retweetCount": 133,
        "sentimentScore": -5.106000000000001e-001,
        "id": 6423,
        "adjustedClose": 5.026200000000000e-002,
        "volume": 1346282318
    },
    {
        "tweetID": 1366857632372256768,
        "financeType": "doge",
        "date": "2021-03-03",
        "fullText": "Very much so &amp; its leader shall be The Doge",
        "replyCount": 62,
        "likesCount": 1347,
        "retweetCount": 133,
        "sentimentScore": 0.000000000000000e+000,
        "id": 6424,
        "adjustedClose": 5.059200000000000e-002,
        "volume": 1093877445
    },
    {
        "tweetID": 1368058884837928960,
        "financeType": "doge",
        "date": "2021-03-06",
        "fullText": "Doge spelled backwards is Egod",
        "replyCount": 134,
        "likesCount": 5413,
        "retweetCount": 195,
        "sentimentScore": 0.000000000000000e+000,
        "id": 6427,
        "adjustedClose": 5.098400000000000e-002,
        "volume": 1480482384
    },
    {
        "tweetID": 1370882536101056512,
        "financeType": "doge",
        "date": "2021-03-14",
        "fullText": "Doge day afternoon",
        "replyCount": 48,
        "likesCount": 664,
        "retweetCount": 30,
        "sentimentScore": 0.000000000000000e+000,
        "id": 6435,
        "adjustedClose": 5.859200000000000e-002,
        "volume": 2752132530
    },
    {
        "tweetID": 1370883943143251968,
        "financeType": "doge",
        "date": "2021-03-14",
        "fullText": "Origin of Doge Day Afternoon: The ancient Romans sacrificed a Dogecoin at the beginning of the Doge Days to appease the rage of Sirius, believing that the star was the cause of the hot, sultry weather.",
        "replyCount": 48,
        "likesCount": 664,
        "retweetCount": 30,
        "sentimentScore": -3.612000000000000e-001,
        "id": 6435,
        "adjustedClose": 5.859200000000000e-002,
        "volume": 2752132530
    },
    {
        "tweetID": 1370885153262817280,
        "financeType": "doge",
        "date": "2021-03-14",
        "fullText": "Why are you so dogematic, they ask",
        "replyCount": 134,
        "likesCount": 5413,
        "retweetCount": 195,
        "sentimentScore": 0.000000000000000e+000,
        "id": 6435,
        "adjustedClose": 5.859200000000000e-002,
        "volume": 2752132530
    },
    {
        "tweetID": 1371600053039722496,
        "financeType": "doge",
        "date": "2021-03-16",
        "fullText": "420M Doge",
        "replyCount": 770,
        "likesCount": 20960,
        "retweetCount": 2570,
        "sentimentScore": 0.000000000000000e+000,
        "id": 6437,
        "adjustedClose": 5.860700000000000e-002,
        "volume": 1393771913
    },
    {
        "tweetID": 1372658385896738816,
        "financeType": "doge",
        "date": "2021-03-19",
        "fullText": "Sometimes it’s about Doge",
        "replyCount": 770,
        "likesCount": 20960,
        "retweetCount": 2570,
        "sentimentScore": 0.000000000000000e+000,
        "id": 6440,
        "adjustedClose": 5.832800000000000e-002,
        "volume": 964747809
    },
    {
        "tweetID": 1377567762919292928,
        "financeType": "doge",
        "date": "2021-04-01",
        "fullText": "SpaceX is going to put a literal Dogecoin on the literal moon",
        "replyCount": 770,
        "likesCount": 20960,
        "retweetCount": 2570,
        "sentimentScore": 0.000000000000000e+000,
        "id": 6453,
        "adjustedClose": 6.198600000000000e-002,
        "volume": 5816046822
    },
    {
        "tweetID": 1382551451185131520,
        "financeType": "doge",
        "date": "2021-04-15",
        "fullText": "Doge Barking at the Moon – Miro",
        "replyCount": 149,
        "likesCount": 4013,
        "retweetCount": 190,
        "sentimentScore": 0.000000000000000e+000,
        "id": 6467,
        "adjustedClose": 1.822070000000000e-001,
        "volume": 17916620386
    },
    {
        "tweetID": 1382552587099062272,
        "financeType": "doge",
        "date": "2021-04-15",
        "fullText": "Doge Barking at the Moon",
        "replyCount": 237,
        "likesCount": 1423,
        "retweetCount": 50,
        "sentimentScore": 0.000000000000000e+000,
        "id": 6467,
        "adjustedClose": 1.822070000000000e-001,
        "volume": 17916620386
    },
    {
        "tweetID": 1387290679794089984,
        "financeType": "doge",
        "date": "2021-04-28",
        "fullText": "The Dogefather SNL May 8",
        "replyCount": 237,
        "likesCount": 1423,
        "retweetCount": 50,
        "sentimentScore": 0.000000000000000e+000,
        "id": 6480,
        "adjustedClose": 3.236820000000000e-001,
        "volume": 14464343767
    },
    {
        "tweetID": 1391523807148527616,
        "financeType": "doge",
        "date": "2021-05-10",
        "fullText": "SpaceX launching satellite Doge-1 to the moon next year – Mission paid for in Doge – 1st crypto in space – 1st meme in space To the mooooonnn!!",
        "replyCount": 149,
        "likesCount": 4013,
        "retweetCount": 190,
        "sentimentScore": 0.000000000000000e+000,
        "id": 6492,
        "adjustedClose": 4.499640000000000e-001,
        "volume": 16514521828
    },
    {
        "tweetID": 1392030108274159616,
        "financeType": "doge",
        "date": "2021-05-11",
        "fullText": "Do you want Tesla to accept Doge?",
        "replyCount": 96563,
        "likesCount": 392471,
        "retweetCount": 94898,
        "sentimentScore": 4.404000000000000e-001,
        "id": 6493,
        "adjustedClose": 4.952310000000000e-001,
        "volume": 14566975476
    },
    {
        "tweetID": 1392974251011895296,
        "financeType": "doge",
        "date": "2021-05-14",
        "fullText": "Working with Doge devs to improve system transaction efficiency. Potentially promising.",
        "replyCount": 96563,
        "likesCount": 392471,
        "retweetCount": 94898,
        "sentimentScore": 7.964000000000000e-001,
        "id": 6496,
        "adjustedClose": 5.596040000000000e-001,
        "volume": 20466177002
    },
    {
        "tweetID": 1393738154889338880,
        "financeType": "doge",
        "date": "2021-05-16",
        "fullText": "Ideally, Doge speeds up block time 10X, increases block size 10X &amp; drops fee 100X. Then it wins hands down.",
        "replyCount": 1008,
        "likesCount": 76197,
        "retweetCount": 6153,
        "sentimentScore": 1.779000000000000e-001,
        "id": 6498,
        "adjustedClose": 5.148950000000000e-001,
        "volume": 9541552064
    },
    {
        "tweetID": 1393749019478970368,
        "financeType": "doge",
        "date": "2021-05-16",
        "fullText": "Only if Doge can’t do it. Big pain in the neck to create another one.",
        "replyCount": 2881,
        "likesCount": 196885,
        "retweetCount": 16485,
        "sentimentScore": -2.960000000000000e-001,
        "id": 6498,
        "adjustedClose": 5.148950000000000e-001,
        "volume": 9541552064
    },
    {
        "tweetID": 1393979913624072192,
        "financeType": "doge",
        "date": "2021-05-16",
        "fullText": "Obnoxious threads like this make me want to go all in on Doge",
        "replyCount": 2881,
        "likesCount": 196885,
        "retweetCount": 16485,
        "sentimentScore": -5.160000000000000e-002,
        "id": 6498,
        "adjustedClose": 5.148950000000000e-001,
        "volume": 9541552064
    },
    {
        "tweetID": 1395328697436033024,
        "financeType": "doge",
        "date": "2021-05-20",
        "fullText": "How much is that Doge in the window?",
        "replyCount": 954,
        "likesCount": 23338,
        "retweetCount": 2666,
        "sentimentScore": 0.000000000000000e+000,
        "id": 6502,
        "adjustedClose": 4.001940000000000e-001,
        "volume": 12415484460
    },
    {
        "tweetID": 1395437522306490368,
        "financeType": "doge",
        "date": "2021-05-20",
        "fullText": "A longtime Tesla supporter gave me the Doge dollar sticker at Giga Berlin",
        "replyCount": 954,
        "likesCount": 23338,
        "retweetCount": 2666,
        "sentimentScore": 2.732000000000000e-001,
        "id": 6502,
        "adjustedClose": 4.001940000000000e-001,
        "volume": 12415484460
    },
    {
        "tweetID": 1395438318095986688,
        "financeType": "doge",
        "date": "2021-05-20",
        "fullText": "Yeah, I haven’t &amp; won’t sell any Doge",
        "replyCount": 1008,
        "likesCount": 76197,
        "retweetCount": 6153,
        "sentimentScore": 2.960000000000000e-001,
        "id": 6502,
        "adjustedClose": 4.001940000000000e-001,
        "volume": 12415484460
    },
    {
        "tweetID": 1396916392629137408,
        "financeType": "doge",
        "date": "2021-05-24",
        "fullText": "If you’d like to help develop Doge, please submit ideas on GitHub &amp;",
        "replyCount": 41,
        "likesCount": 2554,
        "retweetCount": 53,
        "sentimentScore": 7.579000000000000e-001,
        "id": 6506,
        "adjustedClose": 3.661620000000000e-001,
        "volume": 6821088755
    },
    {
        "tweetID": 1396926365996261376,
        "financeType": "doge",
        "date": "2021-05-25",
        "fullText": "Someone suggested changing Dogecoin fees based on phases of the moon, which is pretty awesome haha",
        "replyCount": 77,
        "likesCount": 2095,
        "retweetCount": 79,
        "sentimentScore": 8.834000000000000e-001,
        "id": 6507,
        "adjustedClose": 3.463020000000000e-001,
        "volume": 5544552739
    },
    {
        "tweetID": 1397064185222078464,
        "financeType": "doge",
        "date": "2021-05-25",
        "fullText": "Doge has dogs &amp; memes, whereas the others do not",
        "replyCount": 378,
        "likesCount": 2317,
        "retweetCount": 88,
        "sentimentScore": 0.000000000000000e+000,
        "id": 6507,
        "adjustedClose": 3.463020000000000e-001,
        "volume": 5544552739
    },
    {
        "tweetID": 1397285556954877952,
        "financeType": "doge",
        "date": "2021-05-26",
        "fullText": "Please note Dogecoin has no formal organization &amp; no one reports to me, so my ability to take action is limited",
        "replyCount": 3037,
        "likesCount": 150979,
        "retweetCount": 13440,
        "sentimentScore": -1.082000000000000e-001,
        "id": 6508,
        "adjustedClose": 3.536930000000000e-001,
        "volume": 3355793260
    },
    {
        "tweetID": 1410519466518233088,
        "financeType": "doge",
        "date": "2021-07-01",
        "fullText": "Release the Doge!",
        "replyCount": 41,
        "likesCount": 2554,
        "retweetCount": 53,
        "sentimentScore": 0.000000000000000e+000,
        "id": 6544,
        "adjustedClose": 2.445490000000000e-001,
        "volume": 2463946548
    },
    {
        "tweetID": 1410529698497630208,
        "financeType": "doge",
        "date": "2021-07-01",
        "fullText": "Baby Doge, doo, doo, doo, doo, doo, Baby Doge, doo, doo, doo, doo, doo, Baby Doge, doo, doo, doo, doo, doo, Baby Doge",
        "replyCount": 3037,
        "likesCount": 150979,
        "retweetCount": 13440,
        "sentimentScore": 0.000000000000000e+000,
        "id": 6544,
        "adjustedClose": 2.445490000000000e-001,
        "volume": 2463946548
    },
    {
        "tweetID": 1410797794630070272,
        "financeType": "doge",
        "date": "2021-07-02",
        "fullText": "But can I pay in Doge?",
        "replyCount": 77,
        "likesCount": 2095,
        "retweetCount": 79,
        "sentimentScore": -1.531000000000000e-001,
        "id": 6545,
        "adjustedClose": 2.452640000000000e-001,
        "volume": 1321470954
    },
    {
        "tweetID": 1413396249546563584,
        "financeType": "doge",
        "date": "2021-07-09",
        "fullText": "BTC &amp; ETH are pursuing a multilayer transaction system, but base layer transaction rate is slow &amp; transaction cost is high. There is merit imo to Doge maximizing base layer transaction rate &amp; minimizing transaction cost with exchanges acting as the de facto secondary layer.",
        "replyCount": 378,
        "likesCount": 2317,
        "retweetCount": 88,
        "sentimentScore": 5.719000000000000e-001,
        "id": 6552,
        "adjustedClose": 2.198640000000000e-001,
        "volume": 3045790264
    },
    {
        "tweetID": 1414774945335361536,
        "financeType": "doge",
        "date": "2021-07-13",
        "fullText": "Maybe if it sees a Shiba Inu, the car renders a Dogecoin …",
        "replyCount": 4429,
        "likesCount": 113840,
        "retweetCount": 4658,
        "sentimentScore": 0.000000000000000e+000,
        "id": 6556,
        "adjustedClose": 2.000030000000000e-001,
        "volume": 1035890377
    },
    {
        "tweetID": 1416441034469527552,
        "financeType": "doge",
        "date": "2021-07-17",
        "fullText": "Lil X is hodling his Doge like a champ. Literally never said the word “sell” even once!",
        "replyCount": 4429,
        "likesCount": 113840,
        "retweetCount": 4658,
        "sentimentScore": 7.088000000000000e-001,
        "id": 6560,
        "adjustedClose": 1.861250000000000e-001,
        "volume": 2393120423
    },
    {
        "tweetID": 1429923740607909888,
        "financeType": "doge",
        "date": "2021-08-24",
        "fullText": "Ancient Doges",
        "replyCount": 848,
        "likesCount": 12491,
        "retweetCount": 1462,
        "sentimentScore": 0.000000000000000e+000,
        "id": 6598,
        "adjustedClose": 2.887390000000000e-001,
        "volume": 3143768703
    },
    {
        "tweetID": 1440780474662543360,
        "financeType": "doge",
        "date": "2021-09-23",
        "fullText": "Super important for Doge fees to drop to make things like buying movie tix viable",
        "replyCount": 2215,
        "likesCount": 23835,
        "retweetCount": 4126,
        "sentimentScore": 7.269000000000000e-001,
        "id": 6628,
        "adjustedClose": 2.248320000000000e-001,
        "volume": 1169581249
    },
    {
        "tweetID": 1451623475978833920,
        "financeType": "doge",
        "date": "2021-10-22",
        "fullText": "*In Dogecoin",
        "replyCount": 6542,
        "likesCount": 57811,
        "retweetCount": 10584,
        "sentimentScore": 0.000000000000000e+000,
        "id": 6657,
        "adjustedClose": 2.442210000000000e-001,
        "volume": 1829875043
    },
    {
        "tweetID": 1452334458066149376,
        "financeType": "doge",
        "date": "2021-10-24",
        "fullText": "Out of curiosity, I acquired some ascii hash strings called “Bitcoin, Ethereum &amp; Doge”. That’s it. As I’ve said before, don’t bet the farm on crypto! True value is building products &amp; providing services to your fellow human beings, not money in any form.",
        "replyCount": 6066,
        "likesCount": 368095,
        "retweetCount": 60904,
        "sentimentScore": 6.696000000000000e-001,
        "id": 6659,
        "adjustedClose": 2.770480000000000e-001,
        "volume": 5278760541
    },
    {
        "tweetID": 1452348126753349632,
        "financeType": "doge",
        "date": "2021-10-24",
        "fullText": "Lots of people I talked to on the production lines at Tesla or building rockets at SpaceX own Doge. They aren’t financial experts or Silicon Valley technologists. That’s why I decided to support Doge – it felt like the people’s crypto.",
        "replyCount": 4060,
        "likesCount": 33219,
        "retweetCount": 7162,
        "sentimentScore": 6.369000000000000e-001,
        "id": 6659,
        "adjustedClose": 2.770480000000000e-001,
        "volume": 5278760541
    },
    {
        "tweetID": 1453418189862342656,
        "financeType": "doge",
        "date": "2021-10-27",
        "fullText": "If I send you 2 Doge, will you promise to send me 1 Doge?",
        "replyCount": 6066,
        "likesCount": 368095,
        "retweetCount": 60904,
        "sentimentScore": 3.182000000000000e-001,
        "id": 6662,
        "adjustedClose": 2.376900000000000e-001,
        "volume": 5022822846
    },
    {
        "tweetID": 1454876031232380928,
        "financeType": "doge",
        "date": "2021-10-31",
        "fullText": "Tuition is in Dogecoin &amp; u get a discount if u have a dog",
        "replyCount": 25890,
        "likesCount": 241960,
        "retweetCount": 22062,
        "sentimentScore": 0.000000000000000e+000,
        "id": 6666,
        "adjustedClose": 2.802440000000000e-001,
        "volume": 4224104205
    },
    {
        "tweetID": 1455634905870786560,
        "financeType": "doge",
        "date": "2021-11-03",
        "fullText": "How about my lil doge Floki? He would make a great CEO! His judgment is ??.",
        "replyCount": 5763,
        "likesCount": 25497,
        "retweetCount": 4616,
        "sentimentScore": 7.124000000000000e-001,
        "id": 6669,
        "adjustedClose": 2.694070000000000e-001,
        "volume": 2091380862
    },
    {
        "tweetID": 1463085111600205824,
        "financeType": "doge",
        "date": "2021-11-23",
        "fullText": "Hey what’s going on with your Doge customers? Sounds shady.",
        "replyCount": 4687,
        "likesCount": 24943,
        "retweetCount": 3913,
        "sentimentScore": 0.000000000000000e+000,
        "id": 6689,
        "adjustedClose": 2.265120000000000e-001,
        "volume": 1907278849
    },
    {
        "tweetID": 1463096278171148288,
        "financeType": "doge",
        "date": "2021-11-23",
        "fullText": "Doge holders using Binance should be protected from errors that are not their fault",
        "replyCount": 3274,
        "likesCount": 21846,
        "retweetCount": 3319,
        "sentimentScore": 4.133000000000000e-001,
        "id": 6689,
        "adjustedClose": 2.265120000000000e-001,
        "volume": 1907278849
    },
    {
        "tweetID": 1463193267336581120,
        "financeType": "doge",
        "date": "2021-11-23",
        "fullText": "I don’t use Binance (tried at one point, but signup was too many hoops to jump through), so no inconvenience to me personally. Just raising this issue on behalf of other Doge holders.",
        "replyCount": 3518,
        "likesCount": 19400,
        "retweetCount": 2386,
        "sentimentScore": -8.160000000000000e-001,
        "id": 6689,
        "adjustedClose": 2.265120000000000e-001,
        "volume": 1907278849
    },
    {
        "tweetID": 1470703708677840896,
        "financeType": "doge",
        "date": "2021-12-14",
        "fullText": "Tesla will make some merch buyable with Doge &amp; see how it goes",
        "replyCount": 49984,
        "likesCount": 363960,
        "retweetCount": 53938,
        "sentimentScore": 0.000000000000000e+000,
        "id": 6710,
        "adjustedClose": 1.801570000000000e-001,
        "volume": 6411471551
    },
    {
        "tweetID": 1473914193527070720,
        "financeType": "doge",
        "date": "2021-12-23",
        "fullText": "That’s why I’m pro Doge",
        "replyCount": 4203,
        "likesCount": 30980,
        "retweetCount": 6149,
        "sentimentScore": 0.000000000000000e+000,
        "id": 6719,
        "adjustedClose": 1.844900000000000e-001,
        "volume": 1184481683
    },
    {
        "tweetID": 1481873421390680064,
        "financeType": "doge",
        "date": "2022-01-14",
        "fullText": "Tesla merch buyable with Dogecoin",
        "replyCount": 38725,
        "likesCount": 332825,
        "retweetCount": 51727,
        "sentimentScore": 0.000000000000000e+000,
        "id": 6741,
        "adjustedClose": 1.835490000000000e-001,
        "volume": 5784004926
    },
    {
        "tweetID": 1485953263040188416,
        "financeType": "doge",
        "date": "2022-01-25",
        "fullText": "I will eat a happy meal on tv if accepts Dogecoin",
        "replyCount": 31009,
        "likesCount": 422498,
        "retweetCount": 59390,
        "sentimentScore": 7.184000000000000e-001,
        "id": 6752,
        "adjustedClose": 1.430490000000000e-001,
        "volume": 1347567750
    },
    {
        "tweetID": 1503222294277197824,
        "financeType": "doge",
        "date": "2022-03-14",
        "fullText": "As a general principle, for those looking for advice from this thread, it is generally better to own physical things like a home or stock in companies you think make good products, than dollars when inflation is high. I still own &amp; won’t sell my Bitcoin, Ethereum or Doge fwiw.",
        "likesCount": 59330,
        "retweetCount": 14894,
        "sentimentScore": 8.074000000000000e-001,
        "id": 6800,
        "adjustedClose": 1.140480000000000e-001,
        "volume": 822092169
    },
    {
        "tweetID": 1512954808394731520,
        "financeType": "doge",
        "date": "2022-04-10",
        "fullText": "Maybe even an option to pay in Doge?",
        "likesCount": 34322,
        "retweetCount": 4372,
        "sentimentScore": -1.027000000000000e-001,
        "id": 6827,
        "adjustedClose": 1.495350000000000e-001,
        "volume": 1931829669
    },
    {
        "tweetID": 1529963471248449536,
        "financeType": "doge",
        "date": "2022-05-26",
        "fullText": "Dogecoin Trillionaire, the Movie ??",
        "likesCount": 17427,
        "retweetCount": 2265,
        "sentimentScore": 0.000000000000000e+000,
        "id": 6873,
        "adjustedClose": 7.825200000000000e-002,
        "volume": 711890873
    },
    {
        "tweetID": 1530209049261658112,
        "financeType": "doge",
        "date": "2022-05-27",
        "fullText": "Tesla merch can be bought with Doge, soon SpaceX merch too",
        "likesCount": 203719,
        "retweetCount": 19599,
        "sentimentScore": 0.000000000000000e+000,
        "id": 6874,
        "adjustedClose": 8.133500000000001e-002,
        "volume": 1310057650
    },
    {
        "tweetID": 1531696049064116224,
        "financeType": "doge",
        "date": "2022-05-31",
        "fullText": "And Palmer always forgets to mention that he never wrote a single line of Dogecoin code …",
        "likesCount": 3663,
        "retweetCount": 317,
        "sentimentScore": 0.000000000000000e+000,
        "id": 6878,
        "adjustedClose": 8.586500000000000e-002,
        "volume": 672444588
    },
    {
        "tweetID": 1531699416490557440,
        "financeType": "doge",
        "date": "2022-05-31",
        "fullText": "You’re humble bro. Billy’s sense of humor &amp; irreverence is a big part of why people love Dogecoin.",
        "likesCount": 12204,
        "retweetCount": 1237,
        "sentimentScore": 7.430000000000000e-001,
        "id": 6878,
        "adjustedClose": 8.586500000000000e-002,
        "volume": 672444588
    },
    {
        "tweetID": 1538406040374595584,
        "financeType": "doge",
        "date": "2022-06-19",
        "fullText": "I will keep supporting Dogecoin",
        "likesCount": 396566,
        "retweetCount": 37467,
        "sentimentScore": 4.404000000000000e-001,
        "id": 6897,
        "adjustedClose": 6.039600000000000e-002,
        "volume": 1166163984
    },
    {
        "tweetID": 1544743525585141760,
        "financeType": "doge",
        "date": "2022-07-06",
        "fullText": "Supporting Doge wherever possible",
        "likesCount": 10646,
        "retweetCount": 2085,
        "sentimentScore": 4.404000000000000e-001,
        "id": 6914,
        "adjustedClose": 6.858300000000001e-002,
        "volume": 398926503
    }
]